bookbook/__init__.py
bookbook/filter_links.py
bookbook/html.py
bookbook/html_index.tpl
bookbook/latex.py
bookbook-0.2.dist-info/LICENSE
bookbook-0.2.dist-info/WHEEL
bookbook-0.2.dist-info/METADATA
bookbook-0.2.dist-info/RECORD
