Metadata-Version: 1.2
Name: bookbook
Version: 0.2
Summary: Tools to use a collection of notebooks as 'chapters'
Home-page: https://github.com/takluyver/bookbook
License: UNKNOWN
Author: Thomas Kluyver
Author-email: thomas@kluyver.me.uk
Requires-Python: >=3.5
Classifier: License :: OSI Approved :: MIT License
Classifier: Programming Language :: Python :: 3
Classifier: Topic :: Documentation
Requires-Dist: nbconvert
Requires-Dist: pandocfilters
Requires-Dist: jinja2
